hdf5matfile/__init__.py
hdf5matfile/__version__
hdf5matfile/errors.py
hdf5matfile/loaders.py
hdf5matfile/test/__init__.py
hdf5matfile/test/test_arrays.mat
hdf5matfile/test/test_arrays.py
hdf5matfile/test/test_cells.mat
hdf5matfile/test/test_cells.py
hdf5matfile/test/test_chars.mat
hdf5matfile/test/test_chars.py
hdf5matfile/test/test_empty.mat
hdf5matfile/test/test_integers.mat
hdf5matfile/test/test_integers.py
hdf5matfile/test/test_structs.mat
hdf5matfile/test/test_structs.py
hdf5matfile-0.4.1.dist-info/METADATA
hdf5matfile-0.4.1.dist-info/WHEEL
hdf5matfile-0.4.1.dist-info/top_level.txt
hdf5matfile-0.4.1.dist-info/RECORD
