Metadata-Version: 2.1
Name: hdf5matfile
Version: 0.4.1
Summary: Load data from v7.3 *.mat files.
Home-page: https://github.com/otaithleigh/hdf5matfile
Author: Peter Talley
Author-email: peterctalley@gmail.com
License: MIT
Platform: UNKNOWN
Requires-Python: >=3.7
Requires-Dist: h5py
Requires-Dist: numpy (>=1.15.0)
